.coveragerc
.gitignore
.readthedocs.yml
AUTHORS.txt
CHANGELOG.rst
CONTRIBUTING.md
LICENSE.txt
MANIFEST.in
Makefile
README.md
pyproject.toml
tox.ini
.github/workflows/sdist.yml
.github/workflows/tox.yml
ArchNGV.egg-info/PKG-INFO
ArchNGV.egg-info/SOURCES.txt
ArchNGV.egg-info/dependency_links.txt
ArchNGV.egg-info/entry_points.txt
ArchNGV.egg-info/requires.txt
ArchNGV.egg-info/top_level.txt
archngv/__init__.py
archngv/exceptions.py
archngv/testing.py
archngv/app/__init__.py
archngv/app/__main__.py
archngv/app/logger.py
archngv/app/ngv.py
archngv/app/utils.py
archngv/app/exemplar/launch.sbatch
archngv/app/exemplar/run.sh
archngv/app/exemplar/bioname/MANIFEST.yaml
archngv/app/exemplar/bioname/astrocyte_gap_junction_recipe.xml
archngv/app/exemplar/bioname/cluster.yaml
archngv/app/exemplar/bioname/er_data.json
archngv/app/exemplar/bioname/tns_context.json
archngv/app/exemplar/bioname/tns_distributions.json
archngv/app/exemplar/bioname/tns_parameters.json
archngv/app/snakemake/Snakefile
archngv/building/__init__.py
archngv/building/checks.py
archngv/building/config.py
archngv/building/exporters.py
archngv/building/legacy.py
archngv/building/microdomains.py
archngv/building/types.py
archngv/building/cell_placement/__init__.py
archngv/building/cell_placement/atlas.py
archngv/building/cell_placement/energy.py
archngv/building/cell_placement/export.py
archngv/building/cell_placement/generation.py
archngv/building/cell_placement/pattern.py
archngv/building/cell_placement/positions.py
archngv/building/cell_placement/potentials.py
archngv/building/cell_placement/soma_generation.py
archngv/building/connectivity/__init__.py
archngv/building/connectivity/glialglial.py
archngv/building/connectivity/gliovascular.py
archngv/building/connectivity/neuroglial_generation.py
archngv/building/connectivity/detail/__init__.py
archngv/building/connectivity/detail/gliovascular_generation/__init__.py
archngv/building/connectivity/detail/gliovascular_generation/check.py
archngv/building/connectivity/detail/gliovascular_generation/graph_connect.py
archngv/building/connectivity/detail/gliovascular_generation/graph_reachout.py
