Metadata-Version: 2.1
Name: ArchNGV
Version: 3.3.0
Summary: NGV architecture modules
Author: Blue Brain Project, EPFL
License: 
Project-URL: Homepage, https://github.com/BlueBrain/ArchNGV
Project-URL: Repository, https://github.com/BlueBrain/ArchNGV
Project-URL: Issues, https://github.com/BlueBrain/ArchNGV/issues
Project-URL: Tracker, https://github.com/BlueBrain/ArchNGV/issues
Classifier: Development Status :: 5 - Production/Stable
Classifier: Intended Audience :: Education
Classifier: Intended Audience :: Science/Research
Classifier: Programming Language :: Python
Classifier: Programming Language :: Python :: 3.8
Classifier: Programming Language :: Python :: 3.9
Classifier: Programming Language :: Python :: 3.10
Classifier: Programming Language :: Python :: 3.11
Classifier: Programming Language :: Python :: 3.12
Classifier: Topic :: Scientific/Engineering :: Bio-Informatics
Requires-Python: >=3.9
License-File: LICENSE.txt
License-File: AUTHORS.txt
Requires-Dist: numpy>=1.22
Requires-Dist: h5py>=3.1.0
Requires-Dist: scipy>=1.5.0
Requires-Dist: libsonata>=0.1.21
Requires-Dist: bluepysnap>=1.0
Requires-Dist: cached-property>=1.5
Requires-Dist: voxcell>=3.0.0
Requires-Dist: vascpy>=0.1.0
Requires-Dist: trimesh>=3.17.1
Requires-Dist: scikit-image>=0.18
Requires-Dist: urllib3<1.27,>=1.21.1; python_version <= "3.8"
Provides-Extra: docs
Requires-Dist: sphinx-bluebrain-theme; extra == "docs"
Provides-Extra: all
Requires-Dist: ngv-ctools>=1.0.0; extra == "all"
Requires-Dist: Click>=7.0; extra == "all"
Requires-Dist: numpy-stl>=2.10; extra == "all"
Requires-Dist: openmesh>=1.1.2; extra == "all"
Requires-Dist: pyyaml>=5.0; extra == "all"
Requires-Dist: pandas>=1.1.0; extra == "all"
Requires-Dist: multivoro; extra == "all"
Requires-Dist: MorphIO>=3.2.0; extra == "all"
Requires-Dist: morph-tool>=2.4.0; extra == "all"
Requires-Dist: snakemake>=5.0.0; extra == "all"
Requires-Dist: tmd>=2.0.11; extra == "all"
Requires-Dist: NeuroTS>=3.4.0; extra == "all"
Requires-Dist: diameter-synthesis>=0.5.4; extra == "all"
Requires-Dist: dask[bag,distributed]>=2022.04.1; extra == "all"
Requires-Dist: dask_mpi>=2.0; extra == "all"
Requires-Dist: brain-indexer>=3.0.0; extra == "all"
Requires-Dist: atlas-commons>=0.1.4; extra == "all"
Requires-Dist: meshio>=5.3.4; extra == "all"
